LICENSE.txt
setup.cfg
setup.py
justGZ/Package.py
justGZ/__init__.py
justGZ.egg-info/PKG-INFO
justGZ.egg-info/SOURCES.txt
justGZ.egg-info/dependency_links.txt
justGZ.egg-info/requires.txt
justGZ.egg-info/top_level.txt
justGZ/DATA/100008.jpg
justGZ/DATA/100023.jpg
justGZ/DATA/100053.jpg
justGZ/DATA/100078.jpg
justGZ/DATA/100090.jpg
justGZ/DATA/100122.jpg
justGZ/DATA/100123.jpg
justGZ/DATA/100128.jpg
justGZ/DATA/100134.jpg
justGZ/DATA/100143.jpg
justGZ/DATA/100150.jpg
justGZ/DATA/100157.jpg
justGZ/DATA/100204.jpg
justGZ/DATA/100237.jpg
justGZ/DATA/100259.jpg
justGZ/DATA/100263.jpg
justGZ/DATA/100288.jpg
justGZ/DATA/100295.jpg
justGZ/DATA/100322.jpg
justGZ/DATA/100335.jpg
justGZ/DATA/100380.jpg
justGZ/DATA/100382.jpg
justGZ/DATA/100383.jpg
justGZ/DATA/100402.jpg
justGZ/DATA/100428.jpg
justGZ/DATA/100434.jpg
justGZ/DATA/100444.jpg
justGZ/DATA/100445.jpg
justGZ/DATA/100458.jpg
justGZ/DATA/100474.jpg
justGZ/DATA/100479.jpg
justGZ/DATA/100506.jpg
justGZ/DATA/100513.jpg
justGZ/DATA/100520.jpg
justGZ/DATA/100541.jpg
justGZ/DATA/100561.jpg
justGZ/DATA/100571.jpg
justGZ/DATA/100601.jpg
justGZ/DATA/100623.jpg
justGZ/DATA/100672.jpg
justGZ/DATA/100673.jpg
justGZ/DATA/100724.jpg
justGZ/DATA/100727.jpg
justGZ/DATA/100730.jpg
justGZ/DATA/100740.jpg
justGZ/DATA/100744.jpg
justGZ/DATA/100765.jpg
justGZ/DATA/100774.jpg
justGZ/DATA/100801.jpg
justGZ/DATA/100813.jpg
justGZ/DATA/100821.jpg
justGZ/DATA/100822.jpg
justGZ/DATA/100836.jpg
justGZ/DATA/100852.jpg
justGZ/DATA/100859.jpg
justGZ/DATA/100861.jpg
justGZ/DATA/100867.jpg
justGZ/DATA/100887.jpg
justGZ/DATA/100894.jpg
justGZ/DATA/100938.jpg
justGZ/DATA/100951.jpg
justGZ/DATA/100986.jpg
justGZ/DATA/101007.jpg
justGZ/DATA/101061.jpg
justGZ/DATA/101074.jpg
justGZ/DATA/101092.jpg
justGZ/DATA/101127.jpg
justGZ/DATA/101133.jpg
justGZ/DATA/101135.jpg
justGZ/DATA/101140.jpg
justGZ/DATA/101151.jpg
justGZ/DATA/101164.jpg
justGZ/DATA/101166.jpg
justGZ/DATA/101181.jpg
justGZ/DATA/101232.jpg
justGZ/DATA/101239.jpg
justGZ/DATA/101244.jpg
justGZ/DATA/101246.jpg
justGZ/DATA/101247.jpg
justGZ/DATA/101251.jpg
justGZ/DATA/101275.jpg
justGZ/DATA/101283.jpg
justGZ/DATA/101286.jpg
justGZ/DATA/101290.jpg
