Metadata-Version: 2.1
Name: justGZ
Version: 1.1
Summary: To assist with importing GZ images in colab
Home-page: https://github.com/yazaazou/justGZ
Download-URL: https://github.com/yazaazou/justGZ/archive/refs/tags/1.1.tar.gz
Author: Youssef Zaazou
Author-email: yazaazou@mun.ca
License: MIT
Keywords: SOME,MEANINGFULL,KEYWORDS
Classifier: Development Status :: 3 - Alpha
Classifier: Intended Audience :: Developers
Classifier: Topic :: Software Development :: Build Tools
Classifier: License :: OSI Approved :: MIT License
Classifier: Programming Language :: Python :: 3
Classifier: Programming Language :: Python :: 3.4
Classifier: Programming Language :: Python :: 3.5
Classifier: Programming Language :: Python :: 3.6
License-File: LICENSE.txt
